whatamithinking/bundler/__init__.py
whatamithinking/bundler/_logs.py
whatamithinking/bundler/windows/__init__.py
whatamithinking/bundler/windows/_bundler.py
whatamithinking/bundler/windows/_installer.py
whatamithinking/bundler/windows/template.iss
whatamithinking_bundler-1.1.4.dist-info/METADATA
whatamithinking_bundler-1.1.4.dist-info/WHEEL
whatamithinking_bundler-1.1.4.dist-info/licenses/LICENSE.md
whatamithinking_bundler-1.1.4.dist-info/RECORD
