Metadata-Version: 2.4
Name: whatamithinking-bundler
Version: 1.1.4
Summary: package python apps for deployment on different platforms
Project-URL: Homepage, https://github.com/whatamithinking/bundler
Project-URL: Documentation, https://github.com/whatamithinking/bundler
Project-URL: Repository, https://github.com/whatamithinking/bundler
Project-URL: Issues, https://github.com/whatamithinking/bundler/issues
Author-email: Connor Sherwood Maynes <connormaynes@gmail.com>
License-File: LICENSE.md
Keywords: bundler,installer,packager,windows
Requires-Python: >=3.11
Requires-Dist: jinja2
Requires-Dist: pyinstaller
Requires-Dist: pyinstaller-versionfile
Requires-Dist: whatamithinking-jsonproto
Provides-Extra: dev
Requires-Dist: black; extra == 'dev'
Provides-Extra: test
